dashai_plugin_juanjo/__init__.py
dashai_plugin_juanjo/mlp_image_classifier.py
dashai_plugin_juanjo-0.0.1.dist-info/METADATA
dashai_plugin_juanjo-0.0.1.dist-info/WHEEL
dashai_plugin_juanjo-0.0.1.dist-info/entry_points.txt
dashai_plugin_juanjo-0.0.1.dist-info/RECORD
