Metadata-Version: 2.3
Name: dashai_plugin_juanjo
Version: 0.0.1
Summary: DashAI Plugin description - Test Juanjo
Author: Juan José Alegría
Author-email: juan.jose.alegria@imfd.cl
Keywords: DashAI,Model
Requires-Python: >=3.8
